awstatscleanup/__init__.py
awstatscleanup/libawstatscleanup.py
awstatscleanup/example/testcleanup.py
mds_awstatscleanup-0.1.0.dist-info/METADATA
mds_awstatscleanup-0.1.0.dist-info/RECORD
mds_awstatscleanup-0.1.0.dist-info/WHEEL
mds_awstatscleanup-0.1.0.dist-info/top_level.txt
